legalabs_scrapy_libs/__init__.py
legalabs_scrapy_libs/create_elastic.py
legalabs_scrapy_libs/items.py
legalabs_scrapy_libs/legallabs_spyder.py
legalabs_scrapy_libs/middlewares.py
legalabs_scrapy_libs/pipelines.py
legalabs_scrapy_libs/settings.py
legalabs_scrapy_libs/stopwords.py
legalabs_scrapy_libs/utils.py
legalabs_scrapy_libs/validation_functions.py
legalabs_scrapy_libs/validator.py
legalabs_scrapy_libs/schemas/acordao.yaml
legalabs_scrapy_libs/schemas/processo.yaml
legalabs_scrapy_libs-0.0.23.dist-info/METADATA
legalabs_scrapy_libs-0.0.23.dist-info/WHEEL
legalabs_scrapy_libs-0.0.23.dist-info/top_level.txt
legalabs_scrapy_libs-0.0.23.dist-info/RECORD
